CHANGES
MANIFEST.in
README.md
setup.cfg
setup.py
factory_rest/__init__.py
factory_rest/rest.py
factory_rest.egg-info/PKG-INFO
factory_rest.egg-info/SOURCES.txt
factory_rest.egg-info/dependency_links.txt
factory_rest.egg-info/requires.txt
factory_rest.egg-info/top_level.txt