Metadata-Version: 1.1
Name: factory-rest
Version: 0.0.1
Summary: Extension to factory-boy to create fixtures over http
Home-page: https://github.com/bertonha/factory-boy-rest
Author: Christofer Bertonha
Author-email: christoferbertonha@gmail.com
License: UNKNOWN
Keywords: testing test fixtures
Platform: UNKNOWN
Classifier: Development Status :: 3 - Alpha
Classifier: Intended Audience :: Developers
Classifier: Topic :: Software Development :: Testing
Classifier: Programming Language :: Python :: 2.7
Classifier: Programming Language :: Python :: 3.4
